pbat/Opts.py
pbat/__init__.py
pbat/compile.py
pbat/core.py
pbat/def.lark
pbat/macro.lark
pbat/parsedef.py
pbat/parsemacro.py
pbat/parsescript.py
pbat-0.0.27.dist-info/LICENSE
pbat-0.0.27.dist-info/METADATA
pbat-0.0.27.dist-info/WHEEL
pbat-0.0.27.dist-info/entry_points.txt
pbat-0.0.27.dist-info/top_level.txt
pbat-0.0.27.dist-info/RECORD
