Metadata-Version: 2.2
Name: pbat
Version: 0.0.27
Summary: Batch file preprocessor
Home-page: https://github.com/mugiseyebrows/pbat
Author: Stanislav Doronin
Author-email: mugisbrows@gmail.com
License-File: LICENSE
Requires-Dist: lark
Requires-Dist: pyyaml
Dynamic: author
Dynamic: author-email
Dynamic: description
Dynamic: description-content-type
Dynamic: home-page
Dynamic: requires-dist
Dynamic: summary
